setup.py
distributions_NM_may2020/Binomialdistribution.py
distributions_NM_may2020/Gaussiandistribution.py
distributions_NM_may2020/Generaldistribution.py
distributions_NM_may2020/__init__.py
distributions_NM_may2020.egg-info/PKG-INFO
distributions_NM_may2020.egg-info/SOURCES.txt
distributions_NM_may2020.egg-info/dependency_links.txt
distributions_NM_may2020.egg-info/not-zip-safe
distributions_NM_may2020.egg-info/top_level.txt