Metadata-Version: 1.2
Name: distributions-NM-may2020
Version: 0.1.1
Summary: Gaussian and Binomial distributions
Home-page: UNKNOWN
Author: Nuria Malet Quintar
Author-email: maletq.ds@gmail.com
License: UNKNOWN
Platform: UNKNOWN
Requires-Python: >=3.0
